auth/__init__.py
auth/database.py
auth/main.py
auth/routes.py
auth/server.py
auth/service.py
auth/CAS/__init__.py
auth/CAS/authorization.py
auth/CAS/authorization_sqlite.py
auth/CAS/REST/__init__.py
auth/CAS/REST/client.py
auth/CAS/REST/service.py
auth/CAS/models/__init__.py
auth/CAS/models/db.py
auth/CAS/models/db_sqlite.py
auth/cmd/__init__.py
auth/cmd/server.py
auth-0.9.2.dist-info/licenses/LICENSE
docs/index.rst
auth-0.9.2.dist-info/METADATA
auth-0.9.2.dist-info/WHEEL
auth-0.9.2.dist-info/entry_points.txt
auth-0.9.2.dist-info/top_level.txt
auth-0.9.2.dist-info/RECORD
